admin_reorder/__init__.py
django_modeladmin_reorder_reborn-0.1.4.dist-info/AUTHORS.md
django_modeladmin_reorder_reborn-0.1.4.dist-info/LICENSE
django_modeladmin_reorder_reborn-0.1.4.dist-info/METADATA
django_modeladmin_reorder_reborn-0.1.4.dist-info/WHEEL
django_modeladmin_reorder_reborn-0.1.4.dist-info/top_level.txt
django_modeladmin_reorder_reborn-0.1.4.dist-info/RECORD
