Metadata-Version: 2.1
Name: django-modeladmin-reorder-reborn
Version: 0.1.4
Summary: Custom ordering for the apps and models in the admin app.
Home-page: https://github.com/StalkerRaftik/django-modeladmin-reorder-reborn
Author: Ivan Smirnov
Author-email: IvanSmirnovOP@ya.ru
License: BSD-3-Clause
Classifier: Environment :: Web Environment
Classifier: Framework :: Django
Classifier: Framework :: Django :: 4.1
Classifier: Intended Audience :: Developers
Classifier: License :: OSI Approved :: BSD License
Classifier: Operating System :: OS Independent
Classifier: Programming Language :: Python
Classifier: Topic :: Internet :: WWW/HTTP
Classifier: Topic :: Internet :: WWW/HTTP :: Dynamic Content
Requires-Python: >=3.5
License-File: LICENSE
License-File: AUTHORS.md
Requires-Dist: Django (>=4.1)
